gym_examples/__init__.py
gym_examples/envs/__init__.py
gym_examples/envs/sumo-rl.py
gym_examples/wrappers/__init__.py
gym_examples/wrappers/clip_reward.py
gym_examples/wrappers/discrete_action.py
gym_examples/wrappers/reacher_weighted_reward.py
gym_examples/wrappers/relative_position.py
simiao_sumo_rl_v0-0.0.1.dist-info/METADATA
simiao_sumo_rl_v0-0.0.1.dist-info/WHEEL
simiao_sumo_rl_v0-0.0.1.dist-info/top_level.txt
simiao_sumo_rl_v0-0.0.1.dist-info/RECORD
