Metadata-Version: 2.1
Name: simiao-sumo-rl-v0
Version: 0.0.1
Requires-Dist: gymnasium>=0.26.0
